sqlalchemy_service/__init__.py
sqlalchemy_service/base_db/__init__.py
sqlalchemy_service/base_db/base.py
sqlalchemy_service/base_db/create.py
sqlalchemy_service/base_db/db_configure.py
sqlalchemy_service/base_service/__init__.py
sqlalchemy_service/base_service/_fastapi_mock.py
sqlalchemy_service/base_service/service.py
sqlalchemy_service-1.0.9.dist-info/LICENSE
sqlalchemy_service-1.0.9.dist-info/METADATA
sqlalchemy_service-1.0.9.dist-info/WHEEL
sqlalchemy_service-1.0.9.dist-info/entry_points.txt
sqlalchemy_service-1.0.9.dist-info/RECORD
