Metadata-Version: 2.3
Name: sqlalchemy-service
Version: 1.0.9
Summary: 
License: LICENSE
Keywords: sqlalchemy
Author: prostoLavr (Lawrence Naumov)
Author-email: <prostolawr@gmail.com>
Maintainer: prostoLavr (Lawrence Naumov)
Maintainer-email: <prostolawr@gmail.com>
Requires-Python: >=3.12,<4.0
Classifier: License :: Other/Proprietary License
Classifier: Programming Language :: Python :: 3
Classifier: Programming Language :: Python :: 3.12
Classifier: Programming Language :: Python :: 3.13
Provides-Extra: fastapi
Provides-Extra: mysql
Provides-Extra: postgres
Requires-Dist: aiomysql (>=0.2.0,<0.3.0) ; extra == "mysql"
Requires-Dist: alembic (>=1.14.0,<1.15.0)
Requires-Dist: asyncpg (>=0.30.0,<0.31.0) ; extra == "postgres"
Requires-Dist: fastapi (>=0.115.8,<0.116.0) ; extra == "fastapi"
Requires-Dist: loguru (>=0.7.3,<0.8.0)
Requires-Dist: pydantic-settings (>=2.7.1,<2.8.0)
Project-URL: Homepage, https://github.com/Dianapp-online/sqlalchemy-service
Project-URL: Issues, https://github.com/Dianapp-online/sqlalchemy-service/issues
